Orange3_Educational-0.8.1-py3.11-nspkg.pth
orange3_educational-0.8.1.data/data/help/orange3-educational/.buildinfo
orange3_educational-0.8.1.data/data/help/orange3-educational/genindex.html
orange3_educational-0.8.1.data/data/help/orange3-educational/index.html
orange3_educational-0.8.1.data/data/help/orange3-educational/objects.inv
orange3_educational-0.8.1.data/data/help/orange3-educational/search.html
orange3_educational-0.8.1.data/data/help/orange3-educational/searchindex.js
orange3_educational-0.8.1.data/data/help/orange3-educational/_images/EnKlik-Anketa-Example.png
orange3_educational-0.8.1.data/data/help/orange3-educational/_images/EnKlik-Anketa-stamped.png
orange3_educational-0.8.1.data/data/help/orange3-educational/_images/Google-Sheets-Example.png
orange3_educational-0.8.1.data/data/help/orange3-educational/_images/Google-Sheets-stamped.png
orange3_educational-0.8.1.data/data/help/orange3-educational/_images/Random-Data-Example.png
orange3_educational-0.8.1.data/data/help/orange3-educational/_images/Random-Data1-stamped.png
orange3_educational-0.8.1.data/data/help/orange3-educational/_images/Random-Data2-stamped.png
orange3_educational-0.8.1.data/data/help/orange3-educational/_images/gradient-descent-flow.png
orange3_educational-0.8.1.data/data/help/orange3-educational/_images/gradient-descent-housing.png
orange3_educational-0.8.1.data/data/help/orange3-educational/_images/gradient-descent-stamped.png
orange3_educational-0.8.1.data/data/help/orange3-educational/_images/gradient-descent1.png
orange3_educational-0.8.1.data/data/help/orange3-educational/_images/gradient-descent2.png
orange3_educational-0.8.1.data/data/help/orange3-educational/_images/gradient-descent3.png
orange3_educational-0.8.1.data/data/help/orange3-educational/_images/gradient-descent4.png
orange3_educational-0.8.1.data/data/help/orange3-educational/_images/interactive-kmeans-input.png
orange3_educational-0.8.1.data/data/help/orange3-educational/_images/interactive-kmeans-stamped.png
orange3_educational-0.8.1.dist-info/licenses/LICENSE
orange3_educational-0.8.1.dist-info/METADATA
orange3_educational-0.8.1.dist-info/WHEEL
orange3_educational-0.8.1.dist-info/entry_points.txt
orange3_educational-0.8.1.dist-info/namespace_packages.txt
orange3_educational-0.8.1.dist-info/top_level.txt
orange3_educational-0.8.1.dist-info/RECORD
