Metadata-Version: 2.4
Name: Orange3-Educational
Version: 0.8.1
Summary: Orange Educational add-on for Orange data mining software package.
Home-page: https://github.com/biolab/orange3-educational
Download-URL: https://github.com/biolab/orange3-educational/releases
Author: Bioinformatics Laboratory, FRI UL
Author-email: contact@orange.biolab.si
License: BSD
Keywords: orange3 add-on
License-File: LICENSE
Requires-Dist: Orange3>=3.39.0
Provides-Extra: doc
Requires-Dist: sphinx; extra == "doc"
Requires-Dist: recommonmark; extra == "doc"
Requires-Dist: sphinx_rtd_theme; extra == "doc"
Provides-Extra: test
Requires-Dist: coverage; extra == "test"
Dynamic: author
Dynamic: author-email
Dynamic: description
Dynamic: description-content-type
Dynamic: download-url
Dynamic: home-page
Dynamic: keywords
Dynamic: license
Dynamic: license-file
Dynamic: provides-extra
Dynamic: requires-dist
Dynamic: summary
